{"mexico": {"name": "Mexico", "code": "MEX", "elo": 1912, "rank": 9, "status": "winner", "points": 9, "gd": 6, "coach": "Javier Aguirre", "conf": "CONCACAF", "star": [{"name": "Raúl Jiménez", "goals": 44, "pos": "FW"}, {"name": "Orbelín Pineda", "goals": 12, "pos": "MF"}, {"name": "Edson Álvarez", "goals": 7, "pos": "MF"}, {"name": "Alexis Vega", "goals": 7, "pos": "FW"}], "matches": [{"oppId": "south-africa", "oppCode": "RSA", "gf": 2, "ga": 0, "res": "W", "stage": "group", "xgF": 1.46, "xgA": 0.07}, {"oppId": "south-korea", "oppCode": "KOR", "gf": 1, "ga": 0, "res": "W", "stage": "group", "xgF": 0.53, "xgA": 0.91}, {"oppId": "czechia", "oppCode": "CZE", "gf": 3, "ga": 0, "res": "W", "stage": "group", "xgF": 1.79, "xgA": 0.47}, {"oppId": "ecuador", "oppCode": "ECU", "gf": 2, "ga": 0, "res": "W", "stage": "r32", "xgF": 1.02, "xgA": 0.73}]}, "south-africa": {"name": "South Africa", "code": "RSA", "elo": 1559, "rank": 54, "status": "runner_up", "points": 4, "gd": -1, "coach": "Hugo Broos", "conf": "CAF", "star": [{"name": "Themba Zwane", "goals": 12, "pos": "FW"}, {"name": "Lyle Foster", "goals": 10, "pos": "FW"}, {"name": "Teboho Mokoena", "goals": 9, "pos": "MF"}, {"name": "Oswin Appollis", "goals": 8, "pos": "FW"}], "matches": [{"oppId": "mexico", "oppCode": "MEX", "gf": 0, "ga": 2, "res": "L", "stage": "group", "xgF": 0.07, "xgA": 1.46}, {"oppId": "czechia", "oppCode": "CZE", "gf": 1, "ga": 1, "res": "D", "stage": "group", "xgF": 1.38, "xgA": 1.02}, {"oppId": "south-korea", "oppCode": "KOR", "gf": 1, "ga": 0, "res": "W", "stage": "group", "xgF": 1.1, "xgA": 1}, {"oppId": "canada", "oppCode": "CAN", "gf": 0, "ga": 1, "res": "L", "stage": "r32", "xgF": 0.13, "xgA": 1.32}]}, "south-korea": {"name": "South Korea", "code": "KOR", "elo": 1723, "rank": 31, "status": "contention", "points": 3, "gd": -1, "coach": "Hong Myung-bo", "conf": "AFC", "star": [{"name": "Son Heung-min", "goals": 56, "pos": "FW"}, {"name": "Hwang Hee-chan", "goals": 17, "pos": "MF"}, {"name": "Lee Jae-sung", "goals": 15, "pos": "MF"}, {"name": "Cho Gue-sung", "goals": 12, "pos": "FW"}], "matches": [{"oppId": "czechia", "oppCode": "CZE", "gf": 2, "ga": 1, "res": "W", "stage": "group", "xgF": 2.3, "xgA": 0.83}, {"oppId": "mexico", "oppCode": "MEX", "gf": 0, "ga": 1, "res": "L", "stage": "group", "xgF": 0.91, "xgA": 0.53}, {"oppId": "south-africa", "oppCode": "RSA", "gf": 0, "ga": 1, "res": "L", "stage": "group", "xgF": 1, "xgA": 1.1}]}, "czechia": {"name": "Czechia", "code": "CZE", "elo": 1680, "rank": 48, "status": "eliminated", "points": 1, "gd": -4, "coach": "Miroslav Koubek", "conf": "UEFA", "star": [{"name": "Patrik Schick", "goals": 25, "pos": "FW"}, {"name": "Tomáš Souček", "goals": 17, "pos": "MF"}, {"name": "Vladimír Darida", "goals": 8, "pos": "MF"}, {"name": "Mojmír Chytil", "goals": 6, "pos": "FW"}], "matches": [{"oppId": "south-korea", "oppCode": "KOR", "gf": 1, "ga": 2, "res": "L", "stage": "group", "xgF": 0.83, "xgA": 2.3}, {"oppId": "south-africa", "oppCode": "RSA", "gf": 1, "ga": 1, "res": "D", "stage": "group", "xgF": 1.02, "xgA": 1.38}, {"oppId": "mexico", "oppCode": "MEX", "gf": 0, "ga": 3, "res": "L", "stage": "group", "xgF": 0.47, "xgA": 1.79}]}, "switzerland": {"name": "Switzerland", "code": "SUI", "elo": 1914, "rank": 16, "status": "winner", "points": 7, "gd": 4, "coach": "Murat Yakin", "conf": "UEFA", "star": [{"name": "Breel Embolo", "goals": 24, "pos": "FW"}, {"name": "Granit Xhaka", "goals": 17, "pos": "MF"}, {"name": "Remo Freuler", "goals": 11, "pos": "MF"}, {"name": "Rubén Vargas", "goals": 11, "pos": "FW"}], "matches": [{"oppId": "qatar", "oppCode": "QAT", "gf": 1, "ga": 1, "res": "D", "stage": "group", "xgF": 3.2, "xgA": 0.6}, {"oppId": "bosnia-and-herzegovina", "oppCode": "BIH", "gf": 4, "ga": 1, "res": "W", "stage": "group", "xgF": 2.06, "xgA": 0.23}, {"oppId": "canada", "oppCode": "CAN", "gf": 2, "ga": 1, "res": "W", "stage": "group", "xgF": 1.11, "xgA": 1.66}]}, "canada": {"name": "Canada", "code": "CAN", "elo": 1764, "rank": 32, "status": "runner_up", "points": 4, "gd": 5, "coach": "Jesse Marsch", "conf": "CONCACAF", "star": [{"name": "Jonathan David", "goals": 39, "pos": "FW"}, {"name": "Cyle Larin", "goals": 30, "pos": "FW"}, {"name": "Alphonso Davies", "goals": 15, "pos": "DF"}, {"name": "Jonathan Osorio", "goals": 9, "pos": "MF"}], "matches": [{"oppId": "bosnia-and-herzegovina", "oppCode": "BIH", "gf": 1, "ga": 1, "res": "D", "stage": "group", "xgF": 1.23, "xgA": 0.96}, {"oppId": "qatar", "oppCode": "QAT", "gf": 6, "ga": 0, "res": "W", "stage": "group", "xgF": 4.6, "xgA": 0.22}, {"oppId": "switzerland", "oppCode": "SUI", "gf": 1, "ga": 2, "res": "L", "stage": "group", "xgF": 1.66, "xgA": 1.11}, {"oppId": "south-africa", "oppCode": "RSA", "gf": 1, "ga": 0, "res": "W", "stage": "r32", "xgF": 1.32, "xgA": 0.13}]}, "bosnia-and-herzegovina": {"name": "Bosnia and Herzegovina", "code": "BIH", "elo": 1622, "rank": 61, "status": "best_third", "points": 4, "gd": -1, "coach": "Sergej Barbarez", "conf": "UEFA", "star": [{"name": "Edin Džeko", "goals": 73, "pos": "FW"}, {"name": "Ermedin Demirović", "goals": 4, "pos": "FW"}, {"name": "Haris Tabaković", "goals": 4, "pos": "FW"}, {"name": "Benjamin Tahirović", "goals": 2, "pos": "MF"}], "matches": [{"oppId": "canada", "oppCode": "CAN", "gf": 1, "ga": 1, "res": "D", "stage": "group", "xgF": 0.96, "xgA": 1.23}, {"oppId": "switzerland", "oppCode": "SUI", "gf": 1, "ga": 4, "res": "L", "stage": "group", "xgF": 0.23, "xgA": 2.06}, {"oppId": "qatar", "oppCode": "QAT", "gf": 3, "ga": 1, "res": "W", "stage": "group", "xgF": 0.68, "xgA": 0.77}]}, "qatar": {"name": "Qatar", "code": "QAT", "elo": 1411, "rank": 60, "status": "eliminated", "points": 1, "gd": -8, "coach": "Julen Lopetegui", "conf": "AFC", "star": [{"name": "Almoez Ali", "goals": 55, "pos": "FW"}, {"name": "Hassan Al-Haydos", "goals": 41, "pos": "FW"}, {"name": "Akram Afif", "goals": 39, "pos": "FW"}, {"name": "Boualem Khoukhi", "goals": 20, "pos": "DF"}], "matches": [{"oppId": "switzerland", "oppCode": "SUI", "gf": 1, "ga": 1, "res": "D", "stage": "group", "xgF": 0.6, "xgA": 3.2}, {"oppId": "canada", "oppCode": "CAN", "gf": 0, "ga": 6, "res": "L", "stage": "group", "xgF": 0.22, "xgA": 4.6}, {"oppId": "bosnia-and-herzegovina", "oppCode": "BIH", "gf": 1, "ga": 3, "res": "L", "stage": "group", "xgF": 0.77, "xgA": 0.68}]}, "brazil": {"name": "Brazil", "code": "BRA", "elo": 2009, "rank": 5, "status": "winner", "points": 7, "gd": 6, "coach": "Carlo Ancelotti", "conf": "CONMEBOL", "star": [{"name": "Neymar", "goals": 79, "pos": "FW"}, {"name": "Lucas Paquetá", "goals": 13, "pos": "MF"}, {"name": "Raphinha", "goals": 11, "pos": "FW"}, {"name": "Casemiro", "goals": 9, "pos": "MF"}], "matches": [{"oppId": "morocco", "oppCode": "MAR", "gf": 1, "ga": 1, "res": "D", "stage": "group", "xgF": 1.26, "xgA": 1.37}, {"oppId": "haiti", "oppCode": "HAI", "gf": 3, "ga": 0, "res": "W", "stage": "group", "xgF": 1.75, "xgA": 0.23}, {"oppId": "scotland", "oppCode": "SCO", "gf": 3, "ga": 0, "res": "W", "stage": "group", "xgF": 4.33, "xgA": 1.04}, {"oppId": "japan", "oppCode": "JPN", "gf": 2, "ga": 1, "res": "W", "stage": "r32", "xgF": 1.69, "xgA": 0.23}]}, "morocco": {"name": "Morocco", "code": "MAR", "elo": 1877, "rank": 6, "status": "runner_up", "points": 7, "gd": 3, "coach": "Mohamed Ouahbi", "conf": "CAF", "star": [{"name": "Ayoub El Kaabi", "goals": 22, "pos": "FW"}, {"name": "Brahim Díaz", "goals": 13, "pos": "FW"}, {"name": "Achraf Hakimi", "goals": 11, "pos": "DF"}, {"name": "Soufiane Rahimi", "goals": 11, "pos": "FW"}], "matches": [{"oppId": "brazil", "oppCode": "BRA", "gf": 1, "ga": 1, "res": "D", "stage": "group", "xgF": 1.37, "xgA": 1.26}, {"oppId": "scotland", "oppCode": "SCO", "gf": 1, "ga": 0, "res": "W", "stage": "group", "xgF": 0.99, "xgA": 0.51}, {"oppId": "haiti", "oppCode": "HAI", "gf": 4, "ga": 2, "res": "W", "stage": "group", "xgF": 3.76, "xgA": 0.67}, {"oppId": "netherlands", "oppCode": "NED", "gf": 1, "ga": 1, "res": "D", "stage": "r32", "xgF": null, "xgA": null}]}, "scotland": {"name": "Scotland", "code": "SCO", "elo": 1745, "rank": 41, "status": "contention", "points": 3, "gd": -3, "coach": "Steve Clarke", "conf": "UEFA", "star": [{"name": "John McGinn", "goals": 20, "pos": "MF"}, {"name": "Scott McTominay", "goals": 14, "pos": "MF"}, {"name": "Ché Adams", "goals": 11, "pos": "FW"}, {"name": "Ryan Christie", "goals": 10, "pos": "MF"}], "matches": [{"oppId": "haiti", "oppCode": "HAI", "gf": 1, "ga": 0, "res": "W", "stage": "group", "xgF": 1.05, "xgA": 1.05}, {"oppId": "morocco", "oppCode": "MAR", "gf": 0, "ga": 1, "res": "L", "stage": "group", "xgF": 0.51, "xgA": 0.99}, {"oppId": "brazil", "oppCode": "BRA", "gf": 0, "ga": 3, "res": "L", "stage": "group", "xgF": 1.04, "xgA": 4.33}]}, "haiti": {"name": "Haiti", "code": "HAI", "elo": 1517, "rank": 88, "status": "eliminated", "points": 0, "gd": -6, "coach": "Sébastien Migné", "conf": "CONCACAF", "star": [{"name": "Duckens Nazon", "goals": 44, "pos": "FW"}, {"name": "Frantzdy Pierrot", "goals": 33, "pos": "FW"}, {"name": "Louicius Deedson", "goals": 10, "pos": "FW"}, {"name": "Derrick Etienne Jr.", "goals": 8, "pos": "FW"}], "matches": [{"oppId": "scotland", "oppCode": "SCO", "gf": 0, "ga": 1, "res": "L", "stage": "group", "xgF": 1.05, "xgA": 1.05}, {"oppId": "brazil", "oppCode": "BRA", "gf": 0, "ga": 3, "res": "L", "stage": "group", "xgF": 0.23, "xgA": 1.75}, {"oppId": "morocco", "oppCode": "MAR", "gf": 2, "ga": 4, "res": "L", "stage": "group", "xgF": 0.67, "xgA": 3.76}]}, "united-states": {"name": "United States", "code": "USA", "elo": 1781, "rank": 15, "status": "winner", "points": 6, "gd": 4, "coach": "Mauricio Pochettino", "conf": "CONCACAF", "star": [{"name": "Christian Pulisic", "goals": 33, "pos": "FW"}, {"name": "Ricardo Pepi", "goals": 13, "pos": "FW"}, {"name": "Weston McKennie", "goals": 12, "pos": "MF"}, {"name": "Giovanni Reyna", "goals": 9, "pos": "MF"}], "matches": [{"oppId": "paraguay", "oppCode": "PAR", "gf": 4, "ga": 1, "res": "W", "stage": "group", "xgF": 1.42, "xgA": 0.54}, {"oppId": "australia", "oppCode": "AUS", "gf": 2, "ga": 0, "res": "W", "stage": "group", "xgF": 1.08, "xgA": 0.35}, {"oppId": "turkiye", "oppCode": "TUR", "gf": 2, "ga": 3, "res": "L", "stage": "group", "xgF": 2.01, "xgA": 3.21}]}, "australia": {"name": "Australia", "code": "AUS", "elo": 1800, "rank": 28, "status": "runner_up", "points": 4, "gd": 0, "coach": "Tony Popovic", "conf": "AFC", "star": [{"name": "Jackson Irvine", "goals": 14, "pos": "MF"}, {"name": "Mathew Leckie", "goals": 14, "pos": "FW"}, {"name": "Harry Souttar", "goals": 11, "pos": "DF"}, {"name": "Awer Mabil", "goals": 10, "pos": "FW"}], "matches": [{"oppId": "turkiye", "oppCode": "TUR", "gf": 2, "ga": 0, "res": "W", "stage": "group", "xgF": 1.18, "xgA": 1.36}, {"oppId": "united-states", "oppCode": "USA", "gf": 0, "ga": 2, "res": "L", "stage": "group", "xgF": 0.35, "xgA": 1.08}, {"oppId": "paraguay", "oppCode": "PAR", "gf": 0, "ga": 0, "res": "D", "stage": "group", "xgF": 0.57, "xgA": 0.25}]}, "paraguay": {"name": "Paraguay", "code": "PAR", "elo": 1815, "rank": 37, "status": "contention", "points": 4, "gd": -2, "coach": "Gustavo Alfaro", "conf": "CONMEBOL", "star": [{"name": "Miguel Almirón", "goals": 9, "pos": "MF"}, {"name": "Antonio Sanabria", "goals": 7, "pos": "FW"}, {"name": "Kaku", "goals": 5, "pos": "MF"}, {"name": "Gustavo Gómez", "goals": 4, "pos": "DF"}], "matches": [{"oppId": "united-states", "oppCode": "USA", "gf": 1, "ga": 4, "res": "L", "stage": "group", "xgF": 0.54, "xgA": 1.42}, {"oppId": "turkiye", "oppCode": "TUR", "gf": 1, "ga": 0, "res": "W", "stage": "group", "xgF": 0.32, "xgA": 2.17}, {"oppId": "australia", "oppCode": "AUS", "gf": 0, "ga": 0, "res": "D", "stage": "group", "xgF": 0.25, "xgA": 0.57}, {"oppId": "germany", "oppCode": "GER", "gf": 1, "ga": 1, "res": "D", "stage": "r32", "xgF": null, "xgA": null}]}, "turkiye": {"name": "Turkiye", "code": "TUR", "elo": 1852, "rank": 27, "status": "eliminated", "points": 3, "gd": -2, "coach": "Vincenzo Montella", "conf": "UEFA", "star": [{"name": "Hakan Çalhanoğlu", "goals": 22, "pos": "MF"}, {"name": "Kerem Aktürkoğlu", "goals": 15, "pos": "FW"}, {"name": "Merih Demiral", "goals": 6, "pos": "DF"}, {"name": "İrfan Can Kahveci", "goals": 6, "pos": "FW"}], "matches": [{"oppId": "australia", "oppCode": "AUS", "gf": 0, "ga": 2, "res": "L", "stage": "group", "xgF": 1.36, "xgA": 1.18}, {"oppId": "paraguay", "oppCode": "PAR", "gf": 0, "ga": 1, "res": "L", "stage": "group", "xgF": 2.17, "xgA": 0.32}, {"oppId": "united-states", "oppCode": "USA", "gf": 3, "ga": 2, "res": "W", "stage": "group", "xgF": 3.21, "xgA": 2.01}]}, "germany": {"name": "Germany", "code": "GER", "elo": 1916, "rank": 12, "status": "winner", "points": 6, "gd": 6, "coach": "Julian Nagelsmann", "conf": "UEFA", "star": [{"name": "Kai Havertz", "goals": 21, "pos": "FW"}, {"name": "Leroy Sané", "goals": 16, "pos": "MF"}, {"name": "Leon Goretzka", "goals": 15, "pos": "MF"}, {"name": "Joshua Kimmich", "goals": 11, "pos": "MF"}], "matches": [{"oppId": "curacao", "oppCode": "CUW", "gf": 7, "ga": 1, "res": "W", "stage": "group", "xgF": 4.22, "xgA": 0.41}, {"oppId": "ivory-coast", "oppCode": "CIV", "gf": 2, "ga": 1, "res": "W", "stage": "group", "xgF": 1.89, "xgA": 1.22}, {"oppId": "ecuador", "oppCode": "ECU", "gf": 1, "ga": 2, "res": "L", "stage": "group", "xgF": 0.65, "xgA": 1.27}, {"oppId": "paraguay", "oppCode": "PAR", "gf": 1, "ga": 1, "res": "D", "stage": "r32", "xgF": null, "xgA": null}]}, "ivory-coast": {"name": "Ivory Coast", "code": "CIV", "elo": 1743, "rank": 30, "status": "runner_up", "points": 6, "gd": 2, "coach": "Emerse Faé", "conf": "CAF", "star": [{"name": "Franck Kessié", "goals": 15, "pos": "MF"}, {"name": "Ibrahim Sangaré", "goals": 12, "pos": "MF"}, {"name": "Nicolas Pépé", "goals": 12, "pos": "FW"}, {"name": "Seko Fofana", "goals": 7, "pos": "MF"}], "matches": [{"oppId": "ecuador", "oppCode": "ECU", "gf": 1, "ga": 0, "res": "W", "stage": "group", "xgF": 1.52, "xgA": 1.01}, {"oppId": "germany", "oppCode": "GER", "gf": 1, "ga": 2, "res": "L", "stage": "group", "xgF": 1.22, "xgA": 1.89}, {"oppId": "curacao", "oppCode": "CUW", "gf": 2, "ga": 0, "res": "W", "stage": "group", "xgF": 1.31, "xgA": 0.5}, {"oppId": "norway", "oppCode": "NOR", "gf": 1, "ga": 2, "res": "L", "stage": "r32", "xgF": 1.36, "xgA": 2.02}]}, "ecuador": {"name": "Ecuador", "code": "ECU", "elo": 1902, "rank": 24, "status": "best_third", "points": 4, "gd": 0, "coach": "Sebastián Beccacece", "conf": "CONMEBOL", "star": [{"name": "Enner Valencia", "goals": 49, "pos": "FW"}, {"name": "Gonzalo Plata", "goals": 8, "pos": "MF"}, {"name": "Félix Torres", "goals": 5, "pos": "DF"}, {"name": "Pervis Estupiñán", "goals": 4, "pos": "DF"}], "matches": [{"oppId": "ivory-coast", "oppCode": "CIV", "gf": 0, "ga": 1, "res": "L", "stage": "group", "xgF": 1.01, "xgA": 1.52}, {"oppId": "curacao", "oppCode": "CUW", "gf": 0, "ga": 0, "res": "D", "stage": "group", "xgF": 2.84, "xgA": 0.5}, {"oppId": "germany", "oppCode": "GER", "gf": 2, "ga": 1, "res": "W", "stage": "group", "xgF": 1.27, "xgA": 0.65}, {"oppId": "mexico", "oppCode": "MEX", "gf": 0, "ga": 2, "res": "L", "stage": "r32", "xgF": 0.73, "xgA": 1.02}]}, "curacao": {"name": "Curacao", "code": "CUW", "elo": 1438, "rank": 82, "status": "eliminated", "points": 1, "gd": -8, "coach": "Dick Advocaat", "conf": "CONCACAF", "star": [{"name": "Leandro Bacuna", "goals": 16, "pos": "MF"}, {"name": "Juninho Bacuna", "goals": 14, "pos": "MF"}, {"name": "Gervane Kastaneer", "goals": 9, "pos": "FW"}, {"name": "Kenji Gorré", "goals": 6, "pos": "FW"}], "matches": [{"oppId": "germany", "oppCode": "GER", "gf": 1, "ga": 7, "res": "L", "stage": "group", "xgF": 0.41, "xgA": 4.22}, {"oppId": "ecuador", "oppCode": "ECU", "gf": 0, "ga": 0, "res": "D", "stage": "group", "xgF": 0.5, "xgA": 2.84}, {"oppId": "ivory-coast", "oppCode": "CIV", "gf": 0, "ga": 2, "res": "L", "stage": "group", "xgF": 0.5, "xgA": 1.31}]}, "netherlands": {"name": "Netherlands", "code": "NED", "elo": 1980, "rank": 7, "status": "winner", "points": 7, "gd": 6, "coach": "Ronald Koeman", "conf": "UEFA", "star": [{"name": "Memphis Depay", "goals": 55, "pos": "FW"}, {"name": "Cody Gakpo", "goals": 19, "pos": "FW"}, {"name": "Wout Weghorst", "goals": 14, "pos": "FW"}, {"name": "Donyell Malen", "goals": 13, "pos": "FW"}], "matches": [{"oppId": "japan", "oppCode": "JPN", "gf": 2, "ga": 2, "res": "D", "stage": "group", "xgF": 0.78, "xgA": 0.59}, {"oppId": "sweden", "oppCode": "SWE", "gf": 5, "ga": 1, "res": "W", "stage": "group", "xgF": 2.61, "xgA": 1.01}, {"oppId": "tunisia", "oppCode": "TUN", "gf": 3, "ga": 1, "res": "W", "stage": "group", "xgF": 1.85, "xgA": 0.62}, {"oppId": "morocco", "oppCode": "MAR", "gf": 1, "ga": 1, "res": "D", "stage": "r32", "xgF": null, "xgA": null}]}, "japan": {"name": "Japan", "code": "JPN", "elo": 1910, "rank": 17, "status": "runner_up", "points": 5, "gd": 4, "coach": "Hajime Moriyasu", "conf": "AFC", "star": [{"name": "Ayase Ueda", "goals": 16, "pos": "FW"}, {"name": "Junya Itō", "goals": 15, "pos": "MF"}, {"name": "Daichi Kamada", "goals": 12, "pos": "MF"}, {"name": "Ritsu Dōan", "goals": 11, "pos": "MF"}], "matches": [{"oppId": "netherlands", "oppCode": "NED", "gf": 2, "ga": 2, "res": "D", "stage": "group", "xgF": 0.59, "xgA": 0.78}, {"oppId": "tunisia", "oppCode": "TUN", "gf": 4, "ga": 0, "res": "W", "stage": "group", "xgF": 2.13, "xgA": 0.05}, {"oppId": "sweden", "oppCode": "SWE", "gf": 1, "ga": 1, "res": "D", "stage": "group", "xgF": 1.21, "xgA": 0.64}, {"oppId": "brazil", "oppCode": "BRA", "gf": 1, "ga": 2, "res": "L", "stage": "r32", "xgF": 0.23, "xgA": 1.69}]}, "sweden": {"name": "Sweden", "code": "SWE", "elo": 1742, "rank": 36, "status": "best_third", "points": 4, "gd": 0, "coach": "Graham Potter", "conf": "UEFA", "star": [{"name": "Viktor Gyökeres", "goals": 19, "pos": "FW"}, {"name": "Alexander Isak", "goals": 17, "pos": "FW"}, {"name": "Anthony Elanga", "goals": 6, "pos": "FW"}, {"name": "Ken Sema", "goals": 5, "pos": "FW"}], "matches": [{"oppId": "tunisia", "oppCode": "TUN", "gf": 5, "ga": 1, "res": "W", "stage": "group", "xgF": 1.33, "xgA": 0.28}, {"oppId": "netherlands", "oppCode": "NED", "gf": 1, "ga": 5, "res": "L", "stage": "group", "xgF": 1.01, "xgA": 2.61}, {"oppId": "japan", "oppCode": "JPN", "gf": 1, "ga": 1, "res": "D", "stage": "group", "xgF": 0.64, "xgA": 1.21}, {"oppId": "france", "oppCode": "FRA", "gf": 0, "ga": 3, "res": "L", "stage": "r32", "xgF": 0.65, "xgA": 3.17}]}, "tunisia": {"name": "Tunisia", "code": "TUN", "elo": 1562, "rank": 58, "status": "eliminated", "points": 0, "gd": -10, "coach": "Sabri Lamouchi", "conf": "CAF", "star": [{"name": "Ali Abdi", "goals": 7, "pos": "DF"}, {"name": "Firas Chaouat", "goals": 6, "pos": "FW"}, {"name": "Montassar Talbi", "goals": 4, "pos": "DF"}, {"name": "Ellyes Skhiri", "goals": 4, "pos": "MF"}], "matches": [{"oppId": "sweden", "oppCode": "SWE", "gf": 1, "ga": 5, "res": "L", "stage": "group", "xgF": 0.28, "xgA": 1.33}, {"oppId": "japan", "oppCode": "JPN", "gf": 0, "ga": 4, "res": "L", "stage": "group", "xgF": 0.05, "xgA": 2.13}, {"oppId": "netherlands", "oppCode": "NED", "gf": 1, "ga": 3, "res": "L", "stage": "group", "xgF": 0.62, "xgA": 1.85}]}, "egypt": {"name": "Egypt", "code": "EGY", "elo": 1742, "rank": 26, "status": "contention", "points": 4, "gd": 2, "coach": "Hossam Hassan", "conf": "CAF", "star": [{"name": "Mohamed Salah", "goals": 67, "pos": "FW"}, {"name": "Trézéguet", "goals": 23, "pos": "FW"}, {"name": "Omar Marmoush", "goals": 11, "pos": "FW"}, {"name": "Ramy Rabia", "goals": 5, "pos": "DF"}], "matches": [{"oppId": "belgium", "oppCode": "BEL", "gf": 1, "ga": 1, "res": "D", "stage": "group", "xgF": 1.08, "xgA": 1.35}, {"oppId": "new-zealand", "oppCode": "NZL", "gf": 3, "ga": 1, "res": "W", "stage": "group", "xgF": 1.87, "xgA": 1.24}, {"oppId": "iran", "oppCode": "IRN", "gf": 1, "ga": 1, "res": "D", "stage": "group", "xgF": 0.81, "xgA": 1.83}]}, "iran": {"name": "Iran", "code": "IRN", "elo": 1764, "rank": 21, "status": "contention", "points": 2, "gd": 0, "coach": "Amir Ghalenoei", "conf": "AFC", "star": [{"name": "Mehdi Taremi", "goals": 60, "pos": "FW"}, {"name": "Alireza Jahanbakhsh", "goals": 17, "pos": "MF"}, {"name": "Mohammad Mohebi", "goals": 14, "pos": "MF"}, {"name": "Mehdi Ghayedi", "goals": 10, "pos": "FW"}], "matches": [{"oppId": "new-zealand", "oppCode": "NZL", "gf": 2, "ga": 2, "res": "D", "stage": "group", "xgF": 1.5, "xgA": 1.24}, {"oppId": "belgium", "oppCode": "BEL", "gf": 0, "ga": 0, "res": "D", "stage": "group", "xgF": 0.62, "xgA": 1.79}, {"oppId": "egypt", "oppCode": "EGY", "gf": 1, "ga": 1, "res": "D", "stage": "group", "xgF": 1.83, "xgA": 0.81}]}, "belgium": {"name": "Belgium", "code": "BEL", "elo": 1884, "rank": 10, "status": "contention", "points": 2, "gd": 0, "coach": "Rudi Garcia", "conf": "UEFA", "star": [{"name": "Romelu Lukaku", "goals": 90, "pos": "FW"}, {"name": "Kevin De Bruyne", "goals": 31, "pos": "MF"}, {"name": "Youri Tielemans", "goals": 13, "pos": "MF"}, {"name": "Axel Witsel", "goals": 12, "pos": "MF"}], "matches": [{"oppId": "egypt", "oppCode": "EGY", "gf": 1, "ga": 1, "res": "D", "stage": "group", "xgF": 1.35, "xgA": 1.08}, {"oppId": "iran", "oppCode": "IRN", "gf": 0, "ga": 0, "res": "D", "stage": "group", "xgF": 1.79, "xgA": 0.62}, {"oppId": "new-zealand", "oppCode": "NZL", "gf": 5, "ga": 1, "res": "W", "stage": "group", "xgF": 3.6, "xgA": 0.24}]}, "new-zealand": {"name": "New Zealand", "code": "NZL", "elo": 1534, "rank": 86, "status": "contention", "points": 1, "gd": -2, "coach": "Darren Bazeley", "conf": "OFC", "star": [{"name": "Chris Wood", "goals": 45, "pos": "FW"}, {"name": "Kosta Barbarouses", "goals": 10, "pos": "FW"}, {"name": "Eli Just", "goals": 9, "pos": "FW"}, {"name": "Ben Waine", "goals": 9, "pos": "FW"}], "matches": [{"oppId": "iran", "oppCode": "IRN", "gf": 2, "ga": 2, "res": "D", "stage": "group", "xgF": 1.24, "xgA": 1.5}, {"oppId": "egypt", "oppCode": "EGY", "gf": 1, "ga": 3, "res": "L", "stage": "group", "xgF": 1.24, "xgA": 1.87}, {"oppId": "belgium", "oppCode": "BEL", "gf": 1, "ga": 5, "res": "L", "stage": "group", "xgF": 0.24, "xgA": 3.6}]}, "spain": {"name": "Spain", "code": "ESP", "elo": 2144, "rank": 3, "status": "contention", "points": 4, "gd": 4, "coach": "Luis de la Fuente", "conf": "UEFA", "star": [{"name": "Ferran Torres", "goals": 21, "pos": "FW"}, {"name": "Mikel Oyarzabal", "goals": 15, "pos": "FW"}, {"name": "Dani Olmo", "goals": 12, "pos": "FW"}, {"name": "Lamine Yamal", "goals": 9, "pos": "FW"}], "matches": [{"oppId": "cape-verde", "oppCode": "CPV", "gf": 0, "ga": 0, "res": "D", "stage": "group", "xgF": 2.1, "xgA": 0.2}, {"oppId": "saudi-arabia", "oppCode": "KSA", "gf": 4, "ga": 0, "res": "W", "stage": "group", "xgF": 2.3, "xgA": 0.14}, {"oppId": "uruguay", "oppCode": "URU", "gf": 1, "ga": 0, "res": "W", "stage": "group", "xgF": 0.86, "xgA": 0.2}]}, "uruguay": {"name": "Uruguay", "code": "URU", "elo": 1841, "rank": 19, "status": "contention", "points": 2, "gd": 0, "coach": "Marcelo Bielsa", "conf": "CONMEBOL", "star": [{"name": "Giorgian de Arrascaeta", "goals": 13, "pos": "MF"}, {"name": "Darwin Núñez", "goals": 13, "pos": "FW"}, {"name": "José María Giménez", "goals": 8, "pos": "DF"}, {"name": "Federico Valverde", "goals": 8, "pos": "MF"}], "matches": [{"oppId": "saudi-arabia", "oppCode": "KSA", "gf": 1, "ga": 1, "res": "D", "stage": "group", "xgF": 1.72, "xgA": 0.66}, {"oppId": "cape-verde", "oppCode": "CPV", "gf": 2, "ga": 2, "res": "D", "stage": "group", "xgF": 2.32, "xgA": 0.88}, {"oppId": "spain", "oppCode": "ESP", "gf": 0, "ga": 1, "res": "L", "stage": "group", "xgF": 0.2, "xgA": 0.86}]}, "cape-verde": {"name": "Cape Verde", "code": "CPV", "elo": 1622, "rank": 64, "status": "contention", "points": 2, "gd": 0, "coach": "Bubista", "conf": "CAF", "star": [{"name": "Ryan Mendes", "goals": 22, "pos": "FW"}, {"name": "Garry Rodrigues", "goals": 10, "pos": "MF"}, {"name": "Dailon Livramento", "goals": 7, "pos": "FW"}, {"name": "Gilson Benchimol", "goals": 6, "pos": "FW"}], "matches": [{"oppId": "spain", "oppCode": "ESP", "gf": 0, "ga": 0, "res": "D", "stage": "group", "xgF": 0.2, "xgA": 2.1}, {"oppId": "uruguay", "oppCode": "URU", "gf": 2, "ga": 2, "res": "D", "stage": "group", "xgF": 0.88, "xgA": 2.32}, {"oppId": "saudi-arabia", "oppCode": "KSA", "gf": 0, "ga": 0, "res": "D", "stage": "group", "xgF": 1.46, "xgA": 0.4}]}, "saudi-arabia": {"name": "Saudi Arabia", "code": "KSA", "elo": 1596, "rank": 59, "status": "contention", "points": 1, "gd": -4, "coach": "Georgios Donis", "conf": "AFC", "star": [{"name": "Salem Al-Dawsari", "goals": 27, "pos": "MF"}, {"name": "Saleh Al-Shehri", "goals": 17, "pos": "FW"}, {"name": "Firas Al-Buraikan", "goals": 16, "pos": "FW"}, {"name": "Abdullah Al-Hamdan", "goals": 13, "pos": "FW"}], "matches": [{"oppId": "uruguay", "oppCode": "URU", "gf": 1, "ga": 1, "res": "D", "stage": "group", "xgF": 0.66, "xgA": 1.72}, {"oppId": "spain", "oppCode": "ESP", "gf": 0, "ga": 4, "res": "L", "stage": "group", "xgF": 0.14, "xgA": 2.3}, {"oppId": "cape-verde", "oppCode": "CPV", "gf": 0, "ga": 0, "res": "D", "stage": "group", "xgF": 0.4, "xgA": 1.46}]}, "france": {"name": "France", "code": "FRA", "elo": 2123, "rank": 1, "status": "winner", "points": 6, "gd": 5, "coach": "Didier Deschamps", "conf": "UEFA", "star": [{"name": "Kylian Mbappe", "goals": 60, "pos": "FW"}, {"name": "Ousmane Dembele", "goals": 8, "pos": "FW"}, {"name": "Marcus Thuram", "goals": 7, "pos": "FW"}, {"name": "Adrien Rabiot", "goals": 6, "pos": "MF"}], "matches": [{"oppId": "senegal", "oppCode": "SEN", "gf": 3, "ga": 1, "res": "W", "stage": "group", "xgF": 1.79, "xgA": 0.53}, {"oppId": "iraq", "oppCode": "IRQ", "gf": 3, "ga": 0, "res": "W", "stage": "group", "xgF": 2.67, "xgA": 0.63}, {"oppId": "norway", "oppCode": "NOR", "gf": 4, "ga": 1, "res": "W", "stage": "group", "xgF": 1.31, "xgA": 1.69}, {"oppId": "sweden", "oppCode": "SWE", "gf": 3, "ga": 0, "res": "W", "stage": "r32", "xgF": 3.17, "xgA": 0.65}]}, "norway": {"name": "Norway", "code": "NOR", "elo": 1918, "rank": 23, "status": "runner_up", "points": 6, "gd": 4, "coach": "Stale Solbakken", "conf": "UEFA", "star": [{"name": "Erling Haaland", "goals": 55, "pos": "FW"}, {"name": "Alexander Sorloth", "goals": 26, "pos": "FW"}, {"name": "Antonio Nusa", "goals": 8, "pos": "MF"}, {"name": "Jorgen Strand Larsen", "goals": 6, "pos": "FW"}], "matches": [{"oppId": "iraq", "oppCode": "IRQ", "gf": 4, "ga": 1, "res": "W", "stage": "group", "xgF": 2.52, "xgA": 0.8}, {"oppId": "senegal", "oppCode": "SEN", "gf": 3, "ga": 2, "res": "W", "stage": "group", "xgF": 2.2, "xgA": 1.72}, {"oppId": "france", "oppCode": "FRA", "gf": 1, "ga": 4, "res": "L", "stage": "group", "xgF": 1.69, "xgA": 1.31}, {"oppId": "ivory-coast", "oppCode": "CIV", "gf": 2, "ga": 1, "res": "W", "stage": "r32", "xgF": 2.02, "xgA": 1.36}]}, "senegal": {"name": "Senegal", "code": "SEN", "elo": 1842, "rank": 18, "status": "eliminated", "points": 0, "gd": -3, "coach": "Pape Thiaw", "conf": "CAF", "star": [{"name": "Sadio Mane", "goals": 55, "pos": "FW"}, {"name": "Ismaila Sarr", "goals": 19, "pos": "FW"}, {"name": "Nicolas Jackson", "goals": 8, "pos": "FW"}, {"name": "Idrissa Gana Gueye", "goals": 7, "pos": "MF"}], "matches": [{"oppId": "france", "oppCode": "FRA", "gf": 1, "ga": 3, "res": "L", "stage": "group", "xgF": 0.53, "xgA": 1.79}, {"oppId": "norway", "oppCode": "NOR", "gf": 2, "ga": 3, "res": "L", "stage": "group", "xgF": 1.72, "xgA": 2.2}, {"oppId": "iraq", "oppCode": "IRQ", "gf": 5, "ga": 0, "res": "W", "stage": "group", "xgF": 3.1, "xgA": 0.18}]}, "iraq": {"name": "Iraq", "code": "IRQ", "elo": 1561, "rank": 63, "status": "eliminated", "points": 0, "gd": -6, "coach": "Graham Arnold", "conf": "AFC", "star": [{"name": "Aymen Hussein", "goals": 33, "pos": "FW"}, {"name": "Mohanad Ali", "goals": 27, "pos": "FW"}, {"name": "Ibrahim Bayesh", "goals": 8, "pos": "MF"}, {"name": "Ali Al-Hamadi", "goals": 5, "pos": "FW"}], "matches": [{"oppId": "norway", "oppCode": "NOR", "gf": 1, "ga": 4, "res": "L", "stage": "group", "xgF": 0.8, "xgA": 2.52}, {"oppId": "france", "oppCode": "FRA", "gf": 0, "ga": 3, "res": "L", "stage": "group", "xgF": 0.63, "xgA": 2.67}, {"oppId": "senegal", "oppCode": "SEN", "gf": 0, "ga": 5, "res": "L", "stage": "group", "xgF": 0.18, "xgA": 3.1}]}, "argentina": {"name": "Argentina", "code": "ARG", "elo": 2148, "rank": 2, "status": "winner", "points": 6, "gd": 5, "coach": "Lionel Scaloni", "conf": "CONMEBOL", "star": [{"name": "Lionel Messi", "goals": 116, "pos": "FW"}, {"name": "Lautaro Martinez", "goals": 36, "pos": "FW"}, {"name": "Julian Alvarez", "goals": 14, "pos": "FW"}, {"name": "Nicolas Otamendi", "goals": 8, "pos": "DF"}], "matches": [{"oppId": "algeria", "oppCode": "ALG", "gf": 3, "ga": 0, "res": "W", "stage": "group", "xgF": 1.47, "xgA": 0.3}, {"oppId": "austria", "oppCode": "AUT", "gf": 2, "ga": 0, "res": "W", "stage": "group", "xgF": 2.36, "xgA": 0.53}, {"oppId": "jordan", "oppCode": "JOR", "gf": 3, "ga": 1, "res": "W", "stage": "group", "xgF": 2.14, "xgA": 0.74}]}, "austria": {"name": "Austria", "code": "AUT", "elo": 1836, "rank": 22, "status": "contention", "points": 3, "gd": 0, "coach": "Ralf Rangnick", "conf": "UEFA", "star": [{"name": "Marko Arnautovic", "goals": 47, "pos": "FW"}, {"name": "Marcel Sabitzer", "goals": 26, "pos": "MF"}, {"name": "Michael Gregoritsch", "goals": 24, "pos": "FW"}, {"name": "David Alaba", "goals": 15, "pos": "DF"}], "matches": [{"oppId": "jordan", "oppCode": "JOR", "gf": 3, "ga": 1, "res": "W", "stage": "group", "xgF": 1.69, "xgA": 1.15}, {"oppId": "argentina", "oppCode": "ARG", "gf": 0, "ga": 2, "res": "L", "stage": "group", "xgF": 0.53, "xgA": 2.36}, {"oppId": "algeria", "oppCode": "ALG", "gf": 3, "ga": 3, "res": "D", "stage": "group", "xgF": 1.44, "xgA": 1.62}]}, "algeria": {"name": "Algeria", "code": "ALG", "elo": 1785, "rank": 29, "status": "contention", "points": 3, "gd": -2, "coach": "Vladimir Petkovic", "conf": "CAF", "star": [{"name": "Riyad Mahrez", "goals": 38, "pos": "FW"}, {"name": "Mohamed Amoura", "goals": 19, "pos": "FW"}, {"name": "Amine Gouiri", "goals": 10, "pos": "FW"}, {"name": "Ramy Bensebaini", "goals": 9, "pos": "DF"}], "matches": [{"oppId": "argentina", "oppCode": "ARG", "gf": 0, "ga": 3, "res": "L", "stage": "group", "xgF": 0.3, "xgA": 1.47}, {"oppId": "jordan", "oppCode": "JOR", "gf": 2, "ga": 1, "res": "W", "stage": "group", "xgF": 1.89, "xgA": 0.63}, {"oppId": "austria", "oppCode": "AUT", "gf": 3, "ga": 3, "res": "D", "stage": "group", "xgF": 1.62, "xgA": 1.44}]}, "jordan": {"name": "Jordan", "code": "JOR", "elo": 1628, "rank": 72, "status": "eliminated", "points": 0, "gd": -3, "coach": "Jamal Sellami", "conf": "AFC", "star": [{"name": "Ali Olwan", "goals": 29, "pos": "FW"}, {"name": "Musa Al-Taamari", "goals": 24, "pos": "FW"}, {"name": "Mahmoud Al-Mardi", "goals": 9, "pos": "FW"}, {"name": "Mohammad Abu Zrayq", "goals": 5, "pos": "FW"}], "matches": [{"oppId": "austria", "oppCode": "AUT", "gf": 1, "ga": 3, "res": "L", "stage": "group", "xgF": 1.15, "xgA": 1.69}, {"oppId": "algeria", "oppCode": "ALG", "gf": 1, "ga": 2, "res": "L", "stage": "group", "xgF": 0.63, "xgA": 1.89}, {"oppId": "argentina", "oppCode": "ARG", "gf": 1, "ga": 3, "res": "L", "stage": "group", "xgF": 0.74, "xgA": 2.14}]}, "colombia": {"name": "Colombia", "code": "COL", "elo": 2004, "rank": 11, "status": "winner", "points": 6, "gd": 3, "coach": "Néstor Lorenzo", "conf": "CONMEBOL", "star": [{"name": "James Rodríguez", "goals": 29, "pos": "MF"}, {"name": "Luis Díaz", "goals": 21, "pos": "FW"}, {"name": "Yerry Mina", "goals": 7, "pos": "DF"}, {"name": "Juan Fernando Quintero", "goals": 6, "pos": "MF"}], "matches": [{"oppId": "uzbekistan", "oppCode": "UZB", "gf": 3, "ga": 1, "res": "W", "stage": "group", "xgF": 1.61, "xgA": 1.16}, {"oppId": "dr-congo", "oppCode": "COD", "gf": 1, "ga": 0, "res": "W", "stage": "group", "xgF": 0.98, "xgA": 0.37}, {"oppId": "portugal", "oppCode": "POR", "gf": 0, "ga": 0, "res": "D", "stage": "group", "xgF": 1.63, "xgA": 0.69}]}, "portugal": {"name": "Portugal", "code": "POR", "elo": 1990, "rank": 8, "status": "contention", "points": 4, "gd": 5, "coach": "Roberto Martínez", "conf": "UEFA", "star": [{"name": "Cristiano Ronaldo", "goals": 138, "pos": "FW"}, {"name": "Bruno Fernandes", "goals": 29, "pos": "MF"}, {"name": "Bernardo Silva", "goals": 13, "pos": "MF"}, {"name": "João Félix", "goals": 11, "pos": "FW"}], "matches": [{"oppId": "dr-congo", "oppCode": "COD", "gf": 1, "ga": 1, "res": "D", "stage": "group", "xgF": 0.65, "xgA": 0.87}, {"oppId": "uzbekistan", "oppCode": "UZB", "gf": 5, "ga": 0, "res": "W", "stage": "group", "xgF": 2.61, "xgA": 0.24}, {"oppId": "colombia", "oppCode": "COL", "gf": 0, "ga": 0, "res": "D", "stage": "group", "xgF": 0.69, "xgA": 1.63}]}, "dr-congo": {"name": "DR Congo", "code": "COD", "elo": 1712, "rank": 46, "status": "contention", "points": 1, "gd": -1, "coach": "Sébastien Desabre", "conf": "CAF", "star": [{"name": "Cédric Bakambu", "goals": 21, "pos": "FW"}, {"name": "Meschak Elia", "goals": 12, "pos": "FW"}, {"name": "Yoane Wissa", "goals": 9, "pos": "FW"}, {"name": "Chancel Mbemba", "goals": 7, "pos": "DF"}], "matches": [{"oppId": "portugal", "oppCode": "POR", "gf": 1, "ga": 1, "res": "D", "stage": "group", "xgF": 0.87, "xgA": 0.65}, {"oppId": "colombia", "oppCode": "COL", "gf": 0, "ga": 1, "res": "L", "stage": "group", "xgF": 0.37, "xgA": 0.98}, {"oppId": "uzbekistan", "oppCode": "UZB", "gf": 3, "ga": 1, "res": "W", "stage": "group", "xgF": 2.35, "xgA": 0.27}]}, "uzbekistan": {"name": "Uzbekistan", "code": "UZB", "elo": 1631, "rank": 57, "status": "eliminated", "points": 0, "gd": -7, "coach": "Fabio Cannavaro", "conf": "AFC", "star": [{"name": "Eldor Shomurodov", "goals": 44, "pos": "FW"}, {"name": "Igor Sergeev", "goals": 25, "pos": "FW"}, {"name": "Oston Urunov", "goals": 10, "pos": "MF"}, {"name": "Otabek Shukurov", "goals": 9, "pos": "MF"}], "matches": [{"oppId": "colombia", "oppCode": "COL", "gf": 1, "ga": 3, "res": "L", "stage": "group", "xgF": 1.16, "xgA": 1.61}, {"oppId": "portugal", "oppCode": "POR", "gf": 0, "ga": 5, "res": "L", "stage": "group", "xgF": 0.24, "xgA": 2.61}, {"oppId": "dr-congo", "oppCode": "COD", "gf": 1, "ga": 3, "res": "L", "stage": "group", "xgF": 0.27, "xgA": 2.35}]}, "england": {"name": "England", "code": "ENG", "elo": 2038, "rank": 4, "status": "contention", "points": 4, "gd": 2, "coach": "Thomas Tuchel", "conf": "UEFA", "star": [{"name": "Harry Kane", "goals": 78, "pos": "FW"}, {"name": "Marcus Rashford", "goals": 19, "pos": "FW"}, {"name": "Bukayo Saka", "goals": 14, "pos": "FW"}, {"name": "Declan Rice", "goals": 7, "pos": "MF"}], "matches": [{"oppId": "croatia", "oppCode": "CRO", "gf": 4, "ga": 2, "res": "W", "stage": "group", "xgF": 3.2, "xgA": 0.7}, {"oppId": "ghana", "oppCode": "GHA", "gf": 0, "ga": 0, "res": "D", "stage": "group", "xgF": 1.36, "xgA": 0.17}, {"oppId": "panama", "oppCode": "PAN", "gf": 2, "ga": 0, "res": "W", "stage": "group", "xgF": 1.49, "xgA": 0.57}]}, "ghana": {"name": "Ghana", "code": "GHA", "elo": 1575, "rank": 65, "status": "contention", "points": 4, "gd": 1, "coach": "Carlos Queiroz", "conf": "CAF", "star": [{"name": "Jordan Ayew", "goals": 34, "pos": "FW"}, {"name": "Thomas Partey", "goals": 15, "pos": "MF"}, {"name": "Ernest Nuamah", "goals": 4, "pos": "FW"}, {"name": "Antoine Semenyo", "goals": 3, "pos": "MF"}], "matches": [{"oppId": "panama", "oppCode": "PAN", "gf": 1, "ga": 0, "res": "W", "stage": "group", "xgF": 1.31, "xgA": 0.73}, {"oppId": "england", "oppCode": "ENG", "gf": 0, "ga": 0, "res": "D", "stage": "group", "xgF": 0.17, "xgA": 1.36}, {"oppId": "croatia", "oppCode": "CRO", "gf": 1, "ga": 2, "res": "L", "stage": "group", "xgF": 0.73, "xgA": 0.46}]}, "croatia": {"name": "Croatia", "code": "CRO", "elo": 1905, "rank": 13, "status": "contention", "points": 3, "gd": -1, "coach": "Zlatko Dalić", "conf": "UEFA", "star": [{"name": "Ivan Perišić", "goals": 38, "pos": "FW"}, {"name": "Andrej Kramarić", "goals": 36, "pos": "FW"}, {"name": "Luka Modrić", "goals": 28, "pos": "MF"}, {"name": "Mario Pašalić", "goals": 11, "pos": "MF"}], "matches": [{"oppId": "england", "oppCode": "ENG", "gf": 2, "ga": 4, "res": "L", "stage": "group", "xgF": 0.7, "xgA": 3.2}, {"oppId": "panama", "oppCode": "PAN", "gf": 1, "ga": 0, "res": "W", "stage": "group", "xgF": 1.65, "xgA": 0.55}, {"oppId": "ghana", "oppCode": "GHA", "gf": 2, "ga": 1, "res": "W", "stage": "group", "xgF": 0.46, "xgA": 0.73}]}, "panama": {"name": "Panama", "code": "PAN", "elo": 1658, "rank": 42, "status": "eliminated", "points": 0, "gd": -2, "coach": "Thomas Christiansen", "conf": "CONCACAF", "star": [{"name": "Ismael Díaz", "goals": 17, "pos": "FW"}, {"name": "José Fajardo", "goals": 17, "pos": "FW"}, {"name": "Cecilio Waterman", "goals": 15, "pos": "FW"}, {"name": "Yoel Bárcenas", "goals": 10, "pos": "MF"}], "matches": [{"oppId": "ghana", "oppCode": "GHA", "gf": 0, "ga": 1, "res": "L", "stage": "group", "xgF": 0.73, "xgA": 1.31}, {"oppId": "croatia", "oppCode": "CRO", "gf": 0, "ga": 1, "res": "L", "stage": "group", "xgF": 0.55, "xgA": 1.65}, {"oppId": "england", "oppCode": "ENG", "gf": 0, "ga": 2, "res": "L", "stage": "group", "xgF": 0.57, "xgA": 1.49}]}}